MANIFEST.in
README.md
setup.py
npal/__init__.py
npal/npal.py
npal.egg-info/PKG-INFO
npal.egg-info/SOURCES.txt
npal.egg-info/dependency_links.txt
npal.egg-info/requires.txt
npal.egg-info/top_level.txt