Metadata-Version: 2.1
Name: npal
Version: 0.1.3
Summary: Utilities to access NPAL
Home-page: https://github.com/npal2/npal/
Author: Yoong Hor Meng
Author-email: yoong+del+hm@gmail.com
License: UNKNOWN
Platform: UNKNOWN
Classifier: Programming Language :: Python :: 3
Classifier: License :: OSI Approved :: MIT License
Classifier: Operating System :: OS Independent
Requires-Python: >=3.6
